PyCopyFast/LICENSE
PyCopyFast/README.MD
PyCopyFast/__init__.py
PyCopyFast/requirements.txt
PyCopyFast/thirdparty.json
PyCopyFast-0.21.dist-info/LICENSE.rst
PyCopyFast-0.21.dist-info/METADATA
PyCopyFast-0.21.dist-info/WHEEL
PyCopyFast-0.21.dist-info/top_level.txt
PyCopyFast-0.21.dist-info/RECORD
